feathub/__init__.py
feathub/feathub_client.py
feathub/materialization_group.py
feathub/version.py
feathub/common/__init__.py
feathub/common/config.py
feathub/common/exceptions.py
feathub/common/test_utils.py
feathub/common/types.py
feathub/common/utils.py
feathub/common/validators.py
feathub/dsl/__init__.py
feathub/dsl/abstract_ast_evaluator.py
feathub/dsl/ast.py
feathub/dsl/built_in_func.py
feathub/dsl/expr_lexer_rules.py
feathub/dsl/expr_parser.py
feathub/dsl/expr_utils.py
feathub/examples/__init__.py
feathub/examples/nyc_taxi.py
feathub/examples/nyc_taxi_flink_session.py
feathub/examples/nyc_taxi_spark_client.py
feathub/examples/sample_data.csv
feathub/examples/streaming_average_flink_cli.py
feathub/feature_service/__init__.py
feathub/feature_service/feature_service.py
feathub/feature_service/feature_service_config.py
feathub/feature_service/local_feature_service.py
feathub/feature_tables/__init__.py
feathub/feature_tables/feature_table.py
feathub/feature_tables/format_config.py
feathub/feature_tables/sinks/__init__.py
feathub/feature_tables/sinks/black_hole_sink.py
feathub/feature_tables/sinks/file_system_sink.py
feathub/feature_tables/sinks/hive_sink.py
feathub/feature_tables/sinks/kafka_sink.py
feathub/feature_tables/sinks/memory_store_sink.py
feathub/feature_tables/sinks/mysql_sink.py
feathub/feature_tables/sinks/print_sink.py
feathub/feature_tables/sinks/prometheus_sink.py
feathub/feature_tables/sinks/redis_sink.py
feathub/feature_tables/sinks/sink.py
feathub/feature_tables/sources/__init__.py
feathub/feature_tables/sources/datagen_source.py
feathub/feature_tables/sources/file_system_source.py
feathub/feature_tables/sources/hive_source.py
feathub/feature_tables/sources/kafka_source.py
feathub/feature_tables/sources/memory_store_source.py
feathub/feature_tables/sources/mysql_source.py
feathub/feature_tables/sources/redis_source.py
feathub/feature_views/__init__.py
feathub/feature_views/derived_feature_view.py
feathub/feature_views/feature.py
feathub_nightly-0.2.dev20231231.dist-info/METADATA
feathub_nightly-0.2.dev20231231.dist-info/WHEEL
feathub_nightly-0.2.dev20231231.dist-info/top_level.txt
feathub_nightly-0.2.dev20231231.dist-info/zip-safe
feathub_nightly-0.2.dev20231231.dist-info/RECORD
